airbyte_source_wave_pro/__init__.py
airbyte_source_wave_pro/run.py
airbyte_source_wave_pro/schemas/wave_aws_costs_stream.json
airbyte_source_wave_pro/schemas/wave_azure_costs_stream.json
airbyte_source_wave_pro/schemas/wave_gcp_costs_stream.json
airbyte_source_wave_pro/source.py
airbyte_source_wave_pro/spec.yaml
main.py
airbyte_source_wave_pro-0.1.1.dist-info/METADATA
airbyte_source_wave_pro-0.1.1.dist-info/WHEEL
airbyte_source_wave_pro-0.1.1.dist-info/entry_points.txt
airbyte_source_wave_pro-0.1.1.dist-info/RECORD
