Metadata-Version: 2.3
Name: airbyte-source-wave-pro
Version: 0.1.1
Summary: Source implementation for airbyte-source-wave-pro.
Home-page: https://github.com/kesompochy/airbyte-source-wave-pro
License: MIT
Author: kesompochy
Requires-Python: >=3.9,<3.12
Classifier: License :: OSI Approved :: MIT License
Classifier: Programming Language :: Python :: 3
Classifier: Programming Language :: Python :: 3.9
Classifier: Programming Language :: Python :: 3.10
Classifier: Programming Language :: Python :: 3.11
Requires-Dist: airbyte-cdk (>=0,<1)
Project-URL: Repository, https://github.com/kesompochy/airbyte-source-wave-pro
